chaigpt/__init__.py
chaigpt/__main__.py
chaigpt/chai.py
chaigpt/chai_ai.py
chaigpt/chai_archive.py
chaigpt/chai_argparser.py
chaigpt/chai_bots.py
chaigpt/chai_chat.py
chaigpt/chai_data.py
chaigpt/chai_tools.py
chaigpt-0.0.26.dist-info/METADATA
chaigpt-0.0.26.dist-info/WHEEL
chaigpt-0.0.26.dist-info/entry_points.txt
chaigpt-0.0.26.dist-info/licenses/LICENSE
chaigpt-0.0.26.dist-info/RECORD
