Metadata-Version: 2.1
Name: chaigpt
Version: 0.0.26
Summary: Powerful ChatGPT wrapper adds extensible botswarms for web search, coding, and more.
Project-URL: Homepage, https://github.com/VulcanicAI/ChaiGPT
Project-URL: Bug Tracker, https://github.com/VulcanicAI/ChaiGPT/issues
Author-email: Douglas Graham <doug.n.graham@gmail.com>
License-File: LICENSE
Classifier: License :: OSI Approved :: MIT License
Classifier: Operating System :: OS Independent
Classifier: Programming Language :: Python :: 3
Requires-Python: >=3.7
Requires-Dist: appdirs>=1.4.4
Requires-Dist: beautifulsoup4>=4.12.0
Requires-Dist: duckduckgo-search>=2.8.1
Requires-Dist: jsonpickle>=3.0.1
Requires-Dist: openai>=0.27.0
Requires-Dist: python-dotenv>=1.0.0
Requires-Dist: tiktoken>=0.3.2
Requires-Dist: unicode-slugify>=0.1.5
Requires-Dist: urllib3>=1.26.15
